{
    "DataType": "CustomerData",
    "DataVersion": 0,
    "GameVersion": "0.3.4f4",
    "Dependence": 1.0,
    "PurchaseableProducts": [
        "cocaine"
    ],
    "ProductAffinities": [
        1.0,
        1.0,
        1.0
    ],
    "TimeSinceLastDealCompleted": 1422,
    "TimeSinceLastDealOffered": 1501,
    "OfferedDeals": 73,
    "CompletedDeals": 75,
    "IsContractOffered": false,
    "OfferedContract": {
        "Payment": 0.0,
        "Products": {
            "entries": []
        },
        "DeliveryLocationGUID": "",
        "DeliveryWindow": {
            "IsEnabled": false,
            "WindowStartTime": 1200,
            "WindowEndTime": 1800
        },
        "Expires": false,
        "ExpiresAfter": 0,
        "PickupScheduleIndex": 0,
        "IsCounterOffer": false
    },
    "OfferedContractTime": {
        "elapsedDays": 120,
        "time": 1630
    },
    "TimeSincePlayerApproached": 1175334,
    "TimeSinceInstantDealOffered": 10991,
    "HasBeenRecommended": false
}