{
    "DataType": "CustomerData",
    "DataVersion": 0,
    "GameVersion": "0.3.4f4",
    "Dependence": 0.07999999821186066,
    "PurchaseableProducts": [
        "cocaine"
    ],
    "ProductAffinities": [
        0.1705714464187622,
        0.954737663269043,
        0.8050224781036377
    ],
    "TimeSinceLastDealCompleted": 1104,
    "TimeSinceLastDealOffered": 2184,
    "OfferedDeals": 1,
    "CompletedDeals": 1,
    "IsContractOffered": false,
    "OfferedContract": {
        "Payment": 0.0,
        "Products": {
            "entries": []
        },
        "DeliveryLocationGUID": "",
        "DeliveryWindow": {
            "IsEnabled": false,
            "WindowStartTime": 1200,
            "WindowEndTime": 1800
        },
        "Expires": false,
        "ExpiresAfter": 0,
        "PickupScheduleIndex": 0,
        "IsCounterOffer": false
    },
    "OfferedContractTime": {
        "elapsedDays": 0,
        "time": 0
    },
    "TimeSincePlayerApproached": 1166524,
    "TimeSinceInstantDealOffered": 1166524,
    "HasBeenRecommended": false
}