{
    "DataType": "ChemistData",
    "DataVersion": 0,
    "GameVersion": "0.3.4f4",
    "ID": "mathew_garcia",
    "AssignedProperty": "dockswarehouse",
    "FirstName": "Mathew",
    "LastName": "Garcia",
    "IsMale": true,
    "AppearanceIndex": 6,
    "Position": {
        "x": -75.29277038574219,
        "y": -2.429999828338623,
        "z": -65.22183990478516
    },
    "Rotation": {
        "x": 0.0,
        "y": 0.028968704864382745,
        "z": 0.0,
        "w": 0.9995803236961365
    },
    "GUID": "771deef4-7d43-46f3-b8db-80960e4a4de8",
    "PaidForToday": true,
    "MoveItemData": {
        "TemplateItemJSON": "",
        "GrabbedItemQuantity": 0,
        "SourceGUID": "",
        "DestinationGUID": ""
    }
}