{
    "DataType": "DryingRackData",
    "DataVersion": 0,
    "GameVersion": "0.3.4f4",
    "GUID": "8e647def-0287-4aa8-9203-be4f2662c5be",
    "ItemString": "{\n    \"DataType\": \"ItemData\",\n    \"DataVersion\": 0,\n    \"GameVersion\": \"0.3.4f4\",\n    \"ID\": \"dryingrack\",\n    \"Quantity\": 1\n}",
    "LoadOrder": 0,
    "GridGUID": "fa2d9b23-eb58-43ae-8f8b-7c37a132a46e",
    "OriginCoordinate": {
        "x": 20.0,
        "y": 23.0
    },
    "Rotation": -90,
    "Input": {
        "Items": [
            "{\"DataType\":\"QualityItemData\",\"DataVersion\":0,\"GameVersion\":\"0.3.4f4\",\"ID\":\"cocaleaf\",\"Quantity\":1,\"Quality\":\"Standard\"}"
        ]
    },
    "Output": {
        "Items": [
            "{\"DataType\":\"ItemData\",\"DataVersion\":0,\"GameVersion\":\"0.3.4f4\",\"ID\":\"\",\"Quantity\":0}"
        ]
    },
    "DryingOperations": [
        {
            "ItemID": "cocaleaf",
            "Quantity": 4,
            "StartQuality": 3,
            "Time": 648
        },
        {
            "ItemID": "cocaleaf",
            "Quantity": 12,
            "StartQuality": 2,
            "Time": 216
        },
        {
            "ItemID": "cocaleaf",
            "Quantity": 4,
            "StartQuality": 2,
            "Time": 174
        }
    ]
}