{
    "DataType": "DealerData",
    "DataVersion": 0,
    "GameVersion": "0.3.4f4",
    "ID": "wei_long",
    "Recruited": true,
    "AssignedCustomerIDs": [
        "cranky_frank",
        "genghis_barn",
        "javier_perez",
        "lisa_gardener",
        "mac_cooper",
        "marco_baron",
        "melissa_wood"
    ],
    "ActiveContractGUIDs": [
        "a7045b9d-ce7a-444b-89e4-0daa4cb511ff"
    ],
    "Cash": 2093.60009765625,
    "OverflowItems": {
        "Items": [
            "{\"DataType\":\"ItemData\",\"DataVersion\":0,\"GameVersion\":\"0.3.4f4\",\"ID\":\"\",\"Quantity\":0}",
            "{\"DataType\":\"ItemData\",\"DataVersion\":0,\"GameVersion\":\"0.3.4f4\",\"ID\":\"\",\"Quantity\":0}",
            "{\"DataType\":\"ItemData\",\"DataVersion\":0,\"GameVersion\":\"0.3.4f4\",\"ID\":\"\",\"Quantity\":0}",
            "{\"DataType\":\"ItemData\",\"DataVersion\":0,\"GameVersion\":\"0.3.4f4\",\"ID\":\"\",\"Quantity\":0}",
            "{\"DataType\":\"ItemData\",\"DataVersion\":0,\"GameVersion\":\"0.3.4f4\",\"ID\":\"\",\"Quantity\":0}",
            "{\"DataType\":\"ItemData\",\"DataVersion\":0,\"GameVersion\":\"0.3.4f4\",\"ID\":\"\",\"Quantity\":0}",
            "{\"DataType\":\"ItemData\",\"DataVersion\":0,\"GameVersion\":\"0.3.4f4\",\"ID\":\"\",\"Quantity\":0}",
            "{\"DataType\":\"ItemData\",\"DataVersion\":0,\"GameVersion\":\"0.3.4f4\",\"ID\":\"\",\"Quantity\":0}",
            "{\"DataType\":\"ItemData\",\"DataVersion\":0,\"GameVersion\":\"0.3.4f4\",\"ID\":\"\",\"Quantity\":0}",
            "{\"DataType\":\"ItemData\",\"DataVersion\":0,\"GameVersion\":\"0.3.4f4\",\"ID\":\"\",\"Quantity\":0}"
        ]
    },
    "HasBeenRecommended": true
}