{
    "DataType": "CustomerData",
    "DataVersion": 0,
    "GameVersion": "0.3.4f4",
    "Dependence": 1.0,
    "PurchaseableProducts": [
        "cocaine"
    ],
    "ProductAffinities": [
        1.0,
        1.0,
        1.0
    ],
    "TimeSinceLastDealCompleted": 2282,
    "TimeSinceLastDealOffered": 60,
    "OfferedDeals": 92,
    "CompletedDeals": 59,
    "IsContractOffered": true,
    "OfferedContract": {
        "Payment": 920.0,
        "Products": {
            "entries": [
                {
                    "ProductID": "cocaine",
                    "Quality": 0,
                    "Quantity": 4
                }
            ]
        },
        "DeliveryLocationGUID": "dfef5a22-ac4d-4081-954f-5c6b79a41d58",
        "DeliveryWindow": {
            "IsEnabled": true,
            "WindowStartTime": 0,
            "WindowEndTime": 0
        },
        "Expires": true,
        "ExpiresAfter": 1,
        "PickupScheduleIndex": 0,
        "IsCounterOffer": false
    },
    "OfferedContractTime": {
        "elapsedDays": 121,
        "time": 1420
    },
    "TimeSincePlayerApproached": 8161,
    "TimeSinceInstantDealOffered": 7234,
    "HasBeenRecommended": false
}